dvc_gs/__init__.py
dvc_gs/_dvc_gs_version.py
dvc_gs/tests/__init__.py
dvc_gs/tests/benchmarks.py
dvc_gs/tests/cloud.py
dvc_gs/tests/conftest.py
dvc_gs/tests/fixtures.py
dvc_gs/tests/test_dvc.py
dvc_gs-3.0.1.dist-info/LICENSE
dvc_gs-3.0.1.dist-info/METADATA
dvc_gs-3.0.1.dist-info/WHEEL
dvc_gs-3.0.1.dist-info/top_level.txt
dvc_gs-3.0.1.dist-info/RECORD
